{"/_error":"pages/_error.js","/_app":"pages/_app.js","/admin-console":"pages/admin-console.html","/_document":"pages/_document.js","/analytics":"pages/analytics.html","/api-test":"pages/api-test.html","/appointments":"pages/appointments.html","/care-history":"pages/care-history.html","/care-status":"pages/care-status.html","/episodes":"pages/episodes.html","/facilities":"pages/facilities.html","/help":"pages/help.html","/":"pages/index.html","/my-episodes":"pages/my-episodes.html","/index_new":"pages/index_new.html","/notifications":"pages/notifications.html","/provider-portal":"pages/provider-portal.html","/offline-confirmation":"pages/offline-confirmation.html","/profile":"pages/profile.html","/settings":"pages/settings.html","/specialties":"pages/specialties.html","/symptom-intake":"pages/symptom-intake.html","/supervisor-dashboard":"pages/supervisor-dashboard.html","/test-data":"pages/test-data.html","/test":"pages/test.html","/404":"pages/404.html"}